karasea/__about__.py
karasea/__init__.py
karasea-0.0.1.dist-info/METADATA
karasea-0.0.1.dist-info/WHEEL
karasea-0.0.1.dist-info/licenses/LICENSE.md
karasea-0.0.1.dist-info/RECORD
