Metadata-Version: 2.3
Name: karasea
Version: 0.0.1
Project-URL: Documentation, https://github.com/Pacidus/kara#readme
Project-URL: Issues, https://github.com/Pacidus/kara/issues
Project-URL: Source, https://github.com/Pacidus/kara
Author-email: Pacidus <pacidus@gmail.com>
License-Expression: BSD-3-Clause-Clear
License-File: LICENSE.md
Classifier: Development Status :: 4 - Beta
Classifier: Programming Language :: Python
Classifier: Programming Language :: Python :: 3.8
Classifier: Programming Language :: Python :: 3.9
Classifier: Programming Language :: Python :: 3.10
Classifier: Programming Language :: Python :: 3.11
Classifier: Programming Language :: Python :: 3.12
Classifier: Programming Language :: Python :: Implementation :: CPython
Classifier: Programming Language :: Python :: Implementation :: PyPy
Requires-Python: >=3.8
